iotjoke/__init__.py
iotjoke/iotjoke.py
iotjokepi/__init__.py
iotjokepi/iotjokepi.py
pyiotjokepi-0.2.4.dist-info/LICENSE
pyiotjokepi-0.2.4.dist-info/METADATA
pyiotjokepi-0.2.4.dist-info/WHEEL
pyiotjokepi-0.2.4.dist-info/top_level.txt
pyiotjokepi-0.2.4.dist-info/RECORD
