Metadata-Version: 2.1
Name: pyiotjokepi
Version: 0.2.4
Summary: UNKNOWN
Home-page: https://github.com/dazzHere/IOT-JOKE-PI
Author: Dhanush HL
Author-email: dhanushdazz@gmail.com
License: MIT
Keywords: iot,iot-joke-pi,iot-joke,iot-joker
Platform: UNKNOWN
Classifier: Development Status :: 4 - Beta
Classifier: Environment :: Console
Classifier: Programming Language :: Python :: 3
Requires-Dist: requests
